manimextra/__init__.py
manimextra/algebra/__init__.py
manimextra/algebra/bracket.py
manimextra/algebra/system_of_equations.py
manimextra/algebra/unit_circle.py
manimextra/animations/__init__.py
manimextra/animations/fancy_label.py
manimextra/animations/transform_system.py
manimextra/diagrams/__init__.py
manimextra/diagrams/pie.py
manimextra/geometry/__init__.py
manimextra/geometry/cevians_and_perpendiculars.py
manimextra/geometry/circles.py
manimextra/geometry/default.py
manimextra/geometry/intersection.py
manimextra/geometry/triangle_centers.py
manimextra/useful_in_development.py
manimextra/utils/__init__.py
manimextra/utils/docbuild/__init__.py
manimextra/utils/docbuild/autoaliasattr_directive.py
manimextra/utils/docbuild/autocolor_directive.py
manimextra/utils/docbuild/manim_directive.py
manimextra/utils/docbuild/module_parsing.py
manimextra-1.13.1.dist-info/LICENSE
manimextra-1.13.1.dist-info/METADATA
manimextra-1.13.1.dist-info/WHEEL
manimextra-1.13.1.dist-info/RECORD
